{
  "schemaNamespace" : "CountriesListAPI",
  "input" : {
    "operationSearchPaths" : [
      "**/*.graphql"
    ],
    "schemaSearchPaths" : [
      "**/*.graphqls"
    ]
  },
  "output" : {
    "testMocks" : {
      "none" : {
      }
    },
    "schemaTypes" : {
      "path" : "./CountriesListAPI",
      "moduleType" : {
        "swiftPackageManager" : {
        }
      }
    },
    "operations" : {
      "inSchemaModule" : {
      }
    }
  },
  "schemaDownloadConfiguration" : {
      "downloadMethod" : {
          "introspection" : {
              "endpointURL" : "https://countries.trevorblades.com/",
              "httpMethod" : {
                  "POST" : {
                  }
              },
              "includeDeprecatedInputValues" : false,
              "outputFormat" :"SDL"
          }
      },
      "downloadTimeout" : 60,
      "headers" : [],
      "outputPath" : "./CountryGraphQL/Backend/graphql/schema.graphqls"
  }
}
